[
  {
    "id": 151,
    "category": "수술비",
    "question": "내시경식도정맥류결찰술, 내시경식도정맥류경화요법 몇 종수술비?",
    "answer": "보험 가입시기별 적용기준이 다르면, 보험사별로 지급기준이 다를 수 있습니다.\n1. 1~3종수술비(~08.03.31)의 경우에는 1종 수술비가 지급됩니다.[60회 1회 한도]\n2. 1~5종수술비(~현재)의 경우에는 2종 수술비가 지급됩니다.[60회 1회 한도]"
  },
  {
    "id": 152,
    "category": "수술비",
    "question": "위절제술, 위전절제술, 위부분절제술, 위쐐기절제술, 빌로쓰수술, 위플수술, 위아전절제술, 위상부이단술, 유문동수술 몇 종수술비?",
    "answer": "보험 가입시기별 적용기준이 다르면, 보험사별로 지급기준이 다를 수 있습니다.\n1. 1~3종수술비(~08.03.31)의 경우에는 3종 수술비가 지급됩니다.[관혈수술]\n2. 1~5종수술비(~현재)의 경우에는 4종 수술비가 지급됩니다.[관혈수술]"
  },
  {
    "id": 153,
    "category": "수술비",
    "question": "식도게실 절제술, 식도분문성형술, 식도절개술, 식도종양적출술, 식도근절개술, 위-식도문합술, 위-십이지장문합술, 위-공장문합술, 위유문근 절제술, 위절개술, 위루조성술, 위점막종양적출술, 위용종 절제술, 위궤양 천공봉합술, 유문성형술, 십이지장궤양수술, 십이지장천공봉합술 몇 종수술비?",
    "answer": "보험 가입시기별 적용기준이 다르면, 보험사별로 지급기준이 다를 수 있습니다.\n1. 1~3종수술비(~08.03.31)의 경우에는 2종 수술비가 지급됩니다.[관혈수술]\n2. 1~5종수술비(~현재)의 경우에는 3종 수술비가 지급됩니다.[관혈수술]"
  },
  {
    "id": 154,
    "category": "수술비",
    "question": "경피적 위루조성술(PEG), 내시경적 위종양절제술, 식도협착내시경확장술 몇 종수술비?",
    "answer": "보험 가입시기별 적용기준이 다르면, 보험사별로 지급기준이 다를 수 있습니다.\n1. 1~3종수술비(~08.03.31)의 경우에는 1종 수술비가 지급됩니다.[60회 1회 한도]\n2. 1~5종수술비(~현재)의 경우에는 2종 수술비가 지급됩니다.[60회 1회 한도]"
  },
  {
    "id": 155,
    "category": "수술비",
    "question": "내시경하 위용종절제술, 내시경적 위양성종양절제술 등 내시경, 카테터(관) 등을 이용한 식도, 위, 십이지장의 수술 몇 종수술비?",
    "answer": "보험 가입시기별 적용기준이 다르면, 보험사별로 지급기준이 다를 수 있습니다.\n1. 1~3종수술비(~08.03.31)의 경우에는 1종 수술비가 지급됩니다.[60회 1회 한도]\n2. 1~5종수술비(~현재)의 경우에는 2종 수술비가 지급됩니다.[60회 1회 한도]"
  },
  {
    "id": 156,
    "category": "수술비",
    "question": "위, 식도, 십이지장에 대한 내시경 검사 몇 종수술비?",
    "answer": "해당 수술의 경우에는 종수술비의 정의에 부합되지 않아서 보험금 지급되지 않습니다."
  },
  {
    "id": 157,
    "category": "수술비",
    "question": "간절제술, 간엽절제술, 간낭종적출술, 간내담관문합술, 간내담관공장문합술, 간동맥결찰술(개복), 간파열봉합술, 간내결석적출술(개복), 복강경하 간절제술, 복강경하 간낭포절제술 몇 종수술비?",
    "answer": "보험 가입시기별 적용기준이 다르면, 보험사별로 지급기준이 다를 수 있습니다.\n1. 1~3종수술비(~08.03.31)의 경우에는 2종 수술비가 지급됩니다.[관혈수술]\n2. 1~5종수술비(~현재)의 경우에는 4종 수술비가 지급됩니다.[관혈수술]"
  },
  {
    "id": 158,
    "category": "수술비",
    "question": "간 이식술[수용자에 한함] 몇 종수술비?",
    "answer": "보험 가입시기별 적용기준이 다르면, 보험사별로 지급기준이 다를 수 있습니다.\n1. 1~3종수술비(~08.03.31)의 경우에는 2종 수술비가 지급됩니다.[관혈수술]\n2. 1~5종수술비(~현재)의 경우에는 5종 수술비가 지급됩니다.[관혈수술]"
  },
  {
    "id": 159,
    "category": "수술비",
    "question": "경피적간동맥 화학색전술, 경피적간동맥결찰술 몇 종수술비?",
    "answer": "보험 가입시기별 적용기준이 다르면, 보험사별로 지급기준이 다를 수 있습니다.\n1. 1~3종수술비(~08.03.31)의 경우에는 1종 수술비가 지급됩니다.[60회 1회 한도]\n2. 1~5종수술비(~현재)의 경우에는 2종 수술비가 지급됩니다.[60회 1회 한도]"
  },
  {
    "id": 160,
    "category": "수술비",
    "question": "내시경, 카테터(관) 등을 이용한 간장, 췌장의 수술 몇 종수술비?",
    "answer": "보험 가입시기별 적용기준이 다르면, 보험사별로 지급기준이 다를 수 있습니다.\n1. 1~3종수술비(~08.03.31)의 경우에는 1종 수술비가 지급됩니다.[60일 1회]\n2. 1~5종수술비(~현재)의 경우에는 2종 수술비가 지급됩니다.[60일 1회]"
  },
  {
    "id": 161,
    "category": "수술비",
    "question": "담낭절제술, 복강경하 담낭절제술,담낭공장문합술,담낭위장문합술,담낭공장루조성술,담도재건술, 담도절개술,담도낭종수술, 담도-장문합술,선천성담도폐쇄증수술,담도성형술, 총담관수술,담석제거술(개복), 담낭루술(개복) 몇 종수술비?",
    "answer": "보험 가입시기별 적용기준이 다르면, 보험사별로 지급기준이 다를 수 있습니다.\n1. 1~3종수술비(~08.03.31)의 경우에는 2종 수술비가 지급됩니다.[관혈수술]\n2. 1~5종수술비(~현재)의 경우에는 3종 수술비가 지급됩니다.[관혈수술]"
  },
  {
    "id": 162,
    "category": "수술비",
    "question": "내시경적 담석 레이저제거술, 카테터(관)을 이용한 경피적 담낭루조성술, 담도계 결석치료를 위한 체외충격파쇄석술, 내시경, 카테터(관) 등을 이용한 담낭, 담도 수술, 경피경간 담도배액술, 경피적 담도담낭배액술 몇 종수술비?",
    "answer": "보험 가입시기별 적용기준이 다르면, 보험사별로 지급기준이 다를 수 있습니다.\n1. 1~3종수술비(~08.03.31)의 경우에는 1종 수술비가 지급됩니다.[60일 1회]\n2. 1~5종수술비(~현재)의 경우에는 2종 수술비가 지급됩니다.[60일 1회]"
  },
  {
    "id": 163,
    "category": "수술비",
    "question": "탈장근본수술, 반흔탈장수술, 대퇴탈장수술, 음낭탈장수술, 제대탈장수술, 서혜부탈장수술, 골반부탈장수술, 내장탈장수술, 식도열공탈장수술, 좌골탈장수술, 서혜헤르니아수술, 회음탈장수술, 횡격막탈장수술, 고위결찰술, 복강경하 탈장복원술 몇 종수술비?",
    "answer": "보험 가입시기별 적용기준이 다르면, 보험사별로 지급기준이 다를 수 있습니다.\n1. 1~3종수술비(~08.03.31)의 경우에는 1종 수술비가 지급됩니다.[관혈수술]\n2. 1~5종수술비(~현재)의 경우에는 1종 수술비가 지급됩니다.[관혈수술]"
  },
  {
    "id": 164,
    "category": "수술비",
    "question": "직장탈근본수술, 직장거상고정술, 직장류수술, 직장점막탈성형술 몇 종수술비?",
    "answer": "보험 가입시기별 적용기준이 다르면, 보험사별로 지급기준이 다를 수 있습니다.\n1. 1~3종수술비(~08.03.31)의 경우에는 2종 수술비가 지급됩니다.[관혈수술]\n2. 1~5종수술비(~09.09.30)의 경우에는 2종 수술비가 지급됩니다.[관혈수술]\n2. 1~5종수술비(09.10.01~현재)의 경우에는 1종 수술비가 지급됩니다.[관혈수술]"
  },
  {
    "id": 165,
    "category": "수술비",
    "question": "도수정복술 등 비관혈적정복술 몇 종수술비?",
    "answer": "해당 수술의 경우에는 종수술비의 정의에 부합되지 않아서 보험금 지급되지 않습니다."
  },
  {
    "id": 166,
    "category": "수술비",
    "question": "충수절제술, 복강경하 충수절제술, 충수돌기절제술, 맹장봉축술, 충수주위농양제거술 몇 종수술비?",
    "answer": "보험 가입시기별 적용기준이 다르면, 보험사별로 지급기준이 다를 수 있습니다.\n1. 1~3종수술비(~08.03.31)의 경우에는 1종 수술비가 지급됩니다.[관혈수술]\n2. 1~5종수술비(~현재)의 경우에는 2종 수술비가 지급됩니다.[관혈수술]"
  },
  {
    "id": 167,
    "category": "수술비",
    "question": "국한성복막염 수술 몇 종수술비?",
    "answer": "보험 가입시기별 적용기준이 다르면, 보험사별로 지급기준이 다를 수 있습니다.\n1. 1~3종수술비(~08.03.31)의 경우에는 2종 수술비가 지급됩니다.[관혈수술]\n2. 1~5종수술비(~현재)의 경우에는 2종 수술비가 지급됩니다.[관혈수술]"
  },
  {
    "id": 168,
    "category": "수술비",
    "question": "전신성복막염수술, 결핵성복막염수술, 골반복막염수술, 횡경막하농양수술, 복막염세척 및 배액술 몇 종수술비?",
    "answer": "보험 가입시기별 적용기준이 다르면, 보험사별로 지급기준이 다를 수 있습니다.\n1. 1~3종수술비(~08.03.31)의 경우에는 2종 수술비가 지급됩니다.[관혈수술]\n2. 1~5종수술비(~09.09.30)의 경우에는 3종 수술비가 지급됩니다.[관혈수술]\n2. 1~5종수술비(09.10.01~현재)의 경우에는 2종 수술비가 지급됩니다.[관혈수술]"
  },
  {
    "id": 169,
    "category": "수술비",
    "question": "복막염에 대한 경피적 농양배액술 몇 종수술비?",
    "answer": "보험 가입시기별 적용기준이 다르면, 보험사별로 지급기준이 다를 수 있습니다.\n1. 1~3종수술비(~08.03.31)의 경우에는 1종 수술비가 지급됩니다.[60일 1회]\n2. 1~5종수술비(~현재)의 경우에는 2종 수술비가 지급됩니다.[60일 1회]"
  },
  {
    "id": 170,
    "category": "수술비",
    "question": "소장절제술, 소장종양적출술(개복), 소장게실수술, 소장루조성술, 인공항문조성술, 회장절제술, 회장루조성술, 회맹부절제술, 회장루복원술, 메켈게실수술 몇 종수술비?",
    "answer": "보험 가입시기별 적용기준이 다르면, 보험사별로 지급기준이 다를 수 있습니다.\n1. 1~3종수술비(~08.03.31)의 경우에는 2종 수술비가 지급됩니다.[관혈수술]\n2. 1~5종수술비(~현재)의 경우에는 4종 수술비가 지급됩니다.[관혈수술]"
  },
  {
    "id": 171,
    "category": "수술비",
    "question": "결장절제술, 결장종양적출술(개복), 결장게실수술, 결장루조성술, 결장루복원술 몇 종수술비?",
    "answer": "보험 가입시기별 적용기준이 다르면, 보험사별로 지급기준이 다를 수 있습니다.\n1. 1~3종수술비(~08.03.31)의 경우에는 2종 수술비가 지급됩니다.[관혈수술]\n2. 1~5종수술비(~현재)의 경우에는 4종 수술비가 지급됩니다.[관혈수술]"
  },
  {
    "id": 172,
    "category": "수술비",
    "question": "직장절제술, 직장종양적출술(개복) 몇 종수술비?",
    "answer": "보험 가입시기별 적용기준이 다르면, 보험사별로 지급기준이 다를 수 있습니다.\n1. 1~3종수술비(~08.03.31)의 경우에는 2종 수술비가 지급됩니다.[관혈수술]\n2. 1~5종수술비(~현재)의 경우에는 4종 수술비가 지급됩니다.[관혈수술]"
  },
  {
    "id": 173,
    "category": "수술비",
    "question": "장간막복원술, 장간막종양적출술 몇 종수술비?",
    "answer": "보험 가입시기별 적용기준이 다르면, 보험사별로 지급기준이 다를 수 있습니다.\n1. 1~3종수술비(~08.03.31)의 경우에는 2종 수술비가 지급됩니다.[관혈수술]\n2. 1~5종수술비(~현재)의 경우에는 4종 수술비가 지급됩니다.[관혈수술]"
  },
  {
    "id": 174,
    "category": "수술비",
    "question": "장절제술, 장절개술, 장유착박리술, 장문합술, 장폐쇄증수술(개복), 페색장관유착박리술, 저위전방절제술, 장고정술, 장중첩증수술(관혈) 몇 종수술비?",
    "answer": "보험 가입시기별 적용기준이 다르면, 보험사별로 지급기준이 다를 수 있습니다.\n1. 1~3종수술비(~08.03.31)의 경우에는 2종 수술비가 지급됩니다.[관혈수술]\n2. 1~5종수술비(~현재)의 경우에는 4종 수술비가 지급됩니다.[관혈수술]"
  },
  {
    "id": 175,
    "category": "수술비",
    "question": "내시경적 대장용종절제술, 내시경, 카테터(관) 등을 이용한 수술 몇 종수술비?",
    "answer": "보험 가입시기별 적용기준이 다르면, 보험사별로 지급기준이 다를 수 있습니다.\n1. 1~3종수술비(~08.03.31)의 경우에는 1종 수술비가 지급됩니다.[60일 1회]\n2. 1~5종수술비(~현재)의 경우에는 2종 수술비가 지급됩니다.[60일 1회]"
  },
  {
    "id": 176,
    "category": "수술비",
    "question": "농양(고름)의 절개 배농 몇 종수술비?",
    "answer": "해당 수술의 경우에는 종수술비의 정의에 부합되지 않아서 보험금 지급되지 않습니다."
  },
  {
    "id": 177,
    "category": "수술비",
    "question": "치루근본수술, 치루절제술, 치루절개술, 시톤수술, 누관공적출술 몇 종수술비?",
    "answer": "보험 가입시기별 적용기준이 다르면, 보험사별로 지급기준이 다를 수 있습니다.\n1. 1~3종수술비(~08.03.31)의 경우에는 1종 수술비가 지급됩니다.[관혈수술]\n2. 1~5종수술비(~현재)의 경우에는 1종 수술비가 지급됩니다.[관혈수술]"
  },
  {
    "id": 178,
    "category": "수술비",
    "question": "치핵근본수술, 치핵절제술, 밀리건-모건치핵수술, 퍼거슨치핵절제술, 하모닉치핵절제술, 화이트헤드치핵근본수술, 레이저치핵절제술 몇 종수술비?",
    "answer": "보험 가입시기별 적용기준이 다르면, 보험사별로 지급기준이 다를 수 있습니다.\n1. 1~3종수술비(~08.03.31)의 경우에는 1종 수술비가 지급됩니다.[관혈수술]\n2. 1~5종수술비(~현재)의 경우에는 1종 수술비가 지급됩니다.[관혈수술]"
  },
  {
    "id": 179,
    "category": "수술비",
    "question": "탈항근본수술, 항문성형술 몇 종수술비?",
    "answer": "보험 가입시기별 적용기준이 다르면, 보험사별로 지급기준이 다를 수 있습니다.\n1. 1~3종수술비(~08.03.31)의 경우에는 1종 수술비가 지급됩니다.[관혈수술]\n2. 1~5종수술비(~현재)의 경우에는 1종 수술비가 지급됩니다.[관혈수술]"
  },
  {
    "id": 180,
    "category": "수술비",
    "question": "약물주입경화요법, 치핵결찰술, 고무결찰술, 항문주위 농양배농술, 항문고름제거술, 췌피절제술, 피부꼬리절제술 몇 종수술비?",
    "answer": "해당 수술의 경우에는 종수술비의 정의에 부합되지 않아서 보험금 지급되지 않습니다."
  }
]